{"cameraMode":{"drawMode":0,"name":"Shaded","section":"Shading Mode"},"sceneLighting":true,"audioPlay":false,"sceneViewState":{"m_AlwaysRefresh":false,"showFog":true,"showSkybox":true,"showFlares":true,"showImageEffects":true,"showParticleSystems":true,"showVisualEffectGraphs":true,"m_FxEnabled":true},"in2DMode":false,"pivot":{"x":-1.1875641345977784,"y":3.3822989463806154,"z":2.234065055847168},"rotation":{"x":0.1071101650595665,"y":-0.08982493728399277,"z":0.010984687134623528,"w":0.9905679225921631},"size":4.675252914428711,"orthographic":false}